clasp/__init__.py
clasp/click_callbacks.py
clasp/click_ext.py
clasp/click_types.py
clasp/script_tools.py
clasp/sphinx_click_ext.py
clasp/templates.py
clasp-1.1.10.dist-info/LICENSE
clasp-1.1.10.dist-info/METADATA
clasp-1.1.10.dist-info/WHEEL
clasp-1.1.10.dist-info/entry_points.txt
clasp-1.1.10.dist-info/top_level.txt
clasp-1.1.10.dist-info/zip-safe
clasp-1.1.10.dist-info/RECORD
