Metadata-Version: 2.1
Name: clasp
Version: 1.1.10
Summary: clasp is  tools for command line and subprocess script development
Home-page: https://bitbucket.org/stephenwasilewski/clasp
Author: Stephen Wasilewski
Author-email: stephanwaz@gmail.com
License: Mozilla Public License 2.0 (MPL 2.0)
Project-URL: documentation, https://clasp.readthedocs.io/
Keywords: clasp
Classifier: Development Status :: 2 - Pre-Alpha
Classifier: License :: OSI Approved :: Mozilla Public License 2.0 (MPL 2.0)
Classifier: Natural Language :: English
Classifier: Programming Language :: Python :: 3.6
Classifier: Programming Language :: Python :: 3.7
Requires-Python: >=3.6
License-File: LICENSE
Requires-Dist: click
Requires-Dist: sphinx-click
Requires-Dist: future
Requires-Dist: configparser
Requires-Dist: docutils
Requires-Dist: sphinx
